{
  "scriptId": "319",
  "url": "file:///home/j32587/Code/Dart/quick-attendance/quick-attendance-api/main_test.ts",
  "functions": [
    {
      "functionName": "",
      "ranges": [{ "startOffset": 0, "endOffset": 8648, "count": 1 }],
      "isBlockCoverage": true
    },
    {
      "functionName": "URL",
      "ranges": [{ "startOffset": 146, "endOffset": 194, "count": 5 }],
      "isBlockCoverage": true
    },
    {
      "functionName": "ACCOUNT_URL",
      "ranges": [{ "startOffset": 216, "endOffset": 240, "count": 4 }],
      "isBlockCoverage": true
    },
    {
      "functionName": "ACCOUNT_AUTH_URL",
      "ranges": [{ "startOffset": 267, "endOffset": 296, "count": 0 }],
      "isBlockCoverage": false
    },
    {
      "functionName": "GROUP_URL",
      "ranges": [{ "startOffset": 316, "endOffset": 338, "count": 0 }],
      "isBlockCoverage": false
    },
    {
      "functionName": "GROUP_AUTH_URL",
      "ranges": [{ "startOffset": 363, "endOffset": 390, "count": 0 }],
      "isBlockCoverage": false
    },
    {
      "functionName": "create_and_login_test_users",
      "ranges": [
        { "startOffset": 1176, "endOffset": 2493, "count": 1 },
        { "startOffset": 1329, "endOffset": 1533, "count": 4 },
        { "startOffset": 1576, "endOffset": 2304, "count": 0 },
        { "startOffset": 2347, "endOffset": 2363, "count": 0 },
        { "startOffset": 2409, "endOffset": 2425, "count": 0 },
        { "startOffset": 2470, "endOffset": 2486, "count": 0 }
      ],
      "isBlockCoverage": true
    },
    {
      "functionName": "",
      "ranges": [{ "startOffset": 1964, "endOffset": 2185, "count": 0 }],
      "isBlockCoverage": false
    },
    {
      "functionName": "get_user_information",
      "ranges": [{ "startOffset": 2562, "endOffset": 3823, "count": 1 }],
      "isBlockCoverage": true
    },
    {
      "functionName": "",
      "ranges": [
        { "startOffset": 2711, "endOffset": 3775, "count": 1 },
        { "startOffset": 2829, "endOffset": 3774, "count": 0 }
      ],
      "isBlockCoverage": true
    },
    {
      "functionName": "",
      "ranges": [{ "startOffset": 3308, "endOffset": 3385, "count": 0 }],
      "isBlockCoverage": false
    },
    {
      "functionName": "get_user_information",
      "ranges": [{ "startOffset": 3836, "endOffset": 6476, "count": 0 }],
      "isBlockCoverage": false
    },
    {
      "functionName": "invite_to_group_and_accept",
      "ranges": [{ "startOffset": 6489, "endOffset": 8645, "count": 0 }],
      "isBlockCoverage": false
    }
  ]
}
